# Юсубов Рашид Хазеинович ИКБО-63-23
# Практическое занятие №5. Вопросы виртуализации

П.Н. Советов, РТУ МИРЭА

## Задача 1

Исследование виртуальной стековой машины CPython.

Изучите возможности просмотра байткода ВМ CPython.

```Python
import dis

def foo(x):
    while x:
        x -= 1
    return x + 1

print(dis.dis(foo))
```

Опишите по шагам, что делает каждая из следующих команд (приведите эквивалентное выражение на Python):

 11           0 LOAD_FAST                0 (x)
              2 LOAD_CONST               1 (10)
              4 BINARY_MULTIPLY
              6 LOAD_CONST               2 (42)
              8 BINARY_ADD
             10 RETURN_VALUE

## Решение:

### Байткод:

```Bash
11  0 LOAD_FAST                0 (x)           # Загружает значение переменной x (0 - это индекс переменной)
    2 LOAD_CONST               1 (10)          # Загружает константу 10
    4 BINARY_MULTIPLY                          # Умножает значение x на 10
    6 LOAD_CONST               2 (42)          # Загружает константу 42
    8 BINARY_ADD                              # Сложение результата предыдущего умножения с 42
   10 RETURN_VALUE                            # Возвращает итоговое значение
```

### Описание команд:

1. **`LOAD_FAST 0 (x)`**:
   - **Описание**: Эта команда загружает значение локальной переменной `x`.
   - **Эквивалентное выражение**: `x`
   - **Пример**: Если `x = 5`, то после выполнения этой команды стек будет содержать `5`.

2. **`LOAD_CONST 1 (10)`**:
   - **Описание**: Эта команда загружает константу `10` в стек.
   - **Эквивалентное выражение**: `10`
   - **Пример**: Теперь в стеке будет два значения: `5` (значение `x`) и `10`.

3. **`BINARY_MULTIPLY`**:
   - **Описание**: Эта команда умножает два верхних значения в стеке.
   - **Эквивалентное выражение**: `x * 10`
   - **Пример**: Если в стеке `5` и `10`, результатом будет `50`. Теперь стек будет содержать только `50`.

4. **`LOAD_CONST 2 (42)`**:
   - **Описание**: Эта команда загружает константу `42` в стек.
   - **Эквивалентное выражение**: `42`
   - **Пример**: Теперь в стеке будет `50` и `42`.

5. **`BINARY_ADD`**:
   - **Описание**: Эта команда складывает два верхних значения в стеке.
   - **Эквивалентное выражение**: `50 + 42`
   - **Пример**: Результат сложения `50` и `42` будет `92`. Теперь стек содержит только `92`.

6. **`RETURN_VALUE`**:
   - **Описание**: Эта команда возвращает верхнее значение из стека как результат выполнения функции.
   - **Эквивалентное выражение**: `return 92`
   - **Пример**: Завершает выполнение функции и возвращает значение `92`.

### Полное эквивалентное выражение на Python

Таким образом, весь процесс можно свести к следующему выражению на Python:

```python
def foo(x):
    return (x * 10) + 42
```

Если, например, `x = 5`, то вызов `foo(5)` вернет `92`, что соответствует результату работы байткода.

## Задача 2

Что делает следующий байткод (опишите шаги его работы)? Это известная функция, назовите ее.

```
  5           0 LOAD_CONST               1 (1)
              2 STORE_FAST               1 (r)

  6     >>    4 LOAD_FAST                0 (n)
              6 LOAD_CONST               1 (1)
              8 COMPARE_OP               4 (>)
             10 POP_JUMP_IF_FALSE       30

  7          12 LOAD_FAST                1 (r)
             14 LOAD_FAST                0 (n)
             16 INPLACE_MULTIPLY
             18 STORE_FAST               1 (r)

  8          20 LOAD_FAST                0 (n)
             22 LOAD_CONST               1 (1)
             24 INPLACE_SUBTRACT
             26 STORE_FAST               0 (n)
             28 JUMP_ABSOLUTE            4

  9     >>   30 LOAD_FAST                1 (r)
             32 RETURN_VALUE
```

## Решение:

```
```

## Результат:


## Задача 3

Приведите результаты из задач 1 и 2 для виртуальной машины JVM (Java) или .Net (C#).

## Решение:

```
```

## Результат:


## Задача 4

Работа с qemu. Скачать и установить ISO-образ Alpine Linux для виртуальных машин с официального сайта.
Создать с помощью qemu образ жесткого диска (опция -f qcow2). Объем диска 500 Мб.
Запустить Alpine Linux с CD-ROM.
Установить систему на sda. Изменить motd.
Загрузиться уже с sda.
Прислать полный список команд для установки и загрузки, а также скриншот с motd, где фигурируют ваши имя и фамилия.

## Решение:

```
```

## Результат:


## Задача 5

(после разбора на семинаре и написания у доски базовой части эмулятора древней игровой приставки CHIP-8)

1. Реализовать вывод на экран.
2. Добиться запуска Тетриса.
3. Реализовать ввод с клавиатуры.
4. Добиться успешной работы всех приложений.

[Архив эмулятора CHIP-8](chip.zip)

## Решение:

```
```

## Результат:


## Полезные ссылки

Compiler Explorer: https://godbolt.org/

Байткод CPython: https://docs.python.org/3/library/dis.html

QEMU для Windows: https://www.qemu.org/download/#windows
http://sovietov.com/tmp/mqemu.zip

Документация по QEMU: https://www.qemu.org/docs/master/system/index.html

Старая документация по QEMU (рус.): https://www.opennet.ru/docs/RUS/qemu_doc/

Образы Alpine Linux: https://alpinelinux.org/downloads/

Документация по игровому компьютеру CHIP-8: http://devernay.free.fr/hacks/chip8/C8TECH10.HTM

Учебник по созданию миниатюрной ОС: https://www.cs.bham.ac.uk/~exr/lectures/opsys/10_11/lectures/os-dev.pdf

Nasm: https://nasm.us/

Прерывания BIOS: http://www.ctyme.com/intr/int.htm

Игры в загрузочном секторе: https://github.com/nanochess/Invaders
